{
  "schemaVersion": 1,
  "previews": [
    {
      "labId": "webgpu-exposure-color-pipeline",
      "expectedAcceptanceStatus": "incomplete",
      "artifactDirectory": "artifacts/visual-validation/webgpu-exposure-color-pipeline-v2",
      "backendProof": "mechanism-metrics.json",
      "claimVerdicts": "mechanism-metrics.json",
      "primaryImage": "final.design.png",
      "primaryImageLabel": "Exposure and grading render-target readback",
      "limitations": [
        "The correctness bundle records a native r185 WebGPU backend, but named-adapter timestamp evidence is absent.",
        "The promoted percentile frame is a selection mask, not proof that histogram bin totals, prefix scan, or f64 oracle parity pass.",
        "Lifecycle stability remains unaccepted."
      ],
      "images": [
        { "source": "images/final.design.png", "output": "final.design.png", "encoding": "png-copy", "meaning": "Final exposure, tone-map, LUT, and output-transform readback." },
        { "source": "images/meter-source.png", "output": "meter-source.png", "encoding": "png-copy", "meaning": "Weighted log-luminance meter source diagnostic." },
        { "source": "images/histogram-percentiles.png", "output": "histogram-percentiles.png", "encoding": "png-copy", "meaning": "Percentile-selection mask emitted by the histogram path; not a plotted histogram." },
        { "source": "images/meter-mask.png", "output": "meter-mask.png", "encoding": "png-copy", "meaning": "Metering-mask diagnostic." },
        { "source": "images/tone-map.png", "output": "tone-map.png", "encoding": "png-copy", "meaning": "Tone-map stage diagnostic before the creative LUT." },
        { "source": "images/lut.png", "output": "lut.png", "encoding": "png-copy", "meaning": "Creative LUT stage diagnostic." }
      ]
    },
    {
      "labId": "webgpu-image-pipeline",
      "expectedAcceptanceStatus": "incomplete",
      "artifactDirectory": "artifacts/visual-validation/webgpu-image-pipeline-v2",
      "backendProof": "renderer-info.json",
      "claimVerdicts": "mechanism-metrics.json",
      "primaryImage": "final.design.png",
      "primaryImageLabel": "Final image-pipeline render-target readback",
      "limitations": [
        "Signal, velocity, temporal-reset, and diagnostic readbacks passed the lab artifact validator.",
        "Current-adapter GPU timestamp and lifecycle evidence remain INSUFFICIENT_EVIDENCE."
      ],
      "images": [
        { "source": "images/final.design.png", "output": "final.design.png", "encoding": "png-copy", "meaning": "Final composed output after the single tone map and output transform." },
        { "source": "images/no-post.design.png", "output": "no-post.design.png", "encoding": "png-copy", "meaning": "Readable scene baseline without the post stack." },
        { "source": "images/diagnostics.mosaic.png", "output": "diagnostics.mosaic.png", "encoding": "png-copy", "meaning": "Mosaic assembled from live diagnostic graph outputs." },
        { "source": "images/normal.png", "output": "normal.png", "encoding": "png-copy", "meaning": "Shared normal signal readback." },
        { "source": "images/emissive.png", "output": "emissive.png", "encoding": "png-copy", "meaning": "Shared emissive signal readback." },
        { "source": "images/bloom.png", "output": "bloom.png", "encoding": "png-copy", "meaning": "BloomNode diagnostic readback." },
        { "source": "images/velocity.moving-positive-x.png", "output": "velocity.moving-positive-x.png", "encoding": "png-copy", "meaning": "Moving-velocity fixture with expected positive NDC X sign." },
        { "source": "images/temporal.history.png", "output": "temporal.history.png", "encoding": "png-copy", "meaning": "Temporal history target before camera-cut reset." }
      ]
    }
  ]
}
